memeclip/__init__.py
memeclip/client.py
memeclip/api/__init__.py
memeclip/api/constants.py
memeclip/models/__init__.py
memeclip/models/error.py
memeclip/models/meme.py
memeclip-0.1.0.dist-info/licenses/LICENSE
tests/__init__.py
tests/test_client.py
memeclip-0.1.0.dist-info/METADATA
memeclip-0.1.0.dist-info/WHEEL
memeclip-0.1.0.dist-info/top_level.txt
memeclip-0.1.0.dist-info/RECORD
