Metadata-Version: 2.4
Name: memeclip
Version: 0.1.0
Summary: Official Python SDK for MemeClip's AI Meme Generator API
Home-page: https://github.com/memeclip/memeclip-ai-api
Author: MemeClip
Author-email: service.memeclip@gmail.com
Project-URL: Bug Tracker, https://github.com/memeclip/memeclip-ai-api/issues
Project-URL: Documentation, https://memeclip.ai
Project-URL: Homepage, https://memeclip.ai
Keywords: meme,ai meme generator,video meme generator,video meme,meme image
Classifier: Programming Language :: Python :: 3
Classifier: Programming Language :: Python :: 3.7
Classifier: Programming Language :: Python :: 3.8
Classifier: Programming Language :: Python :: 3.9
Classifier: Programming Language :: Python :: 3.10
Classifier: Programming Language :: Python :: 3.11
Classifier: Programming Language :: Python :: 3.12
Classifier: License :: OSI Approved :: MIT License
Classifier: Operating System :: OS Independent
Classifier: Topic :: Multimedia :: Graphics
Classifier: Topic :: Software Development :: Libraries :: Python Modules
Requires-Python: >=3.7
License-File: LICENSE
Requires-Dist: requests>=2.25.0
Requires-Dist: pillow>=8.0.0
Dynamic: author
Dynamic: author-email
Dynamic: classifier
Dynamic: description
Dynamic: description-content-type
Dynamic: home-page
Dynamic: keywords
Dynamic: license-file
Dynamic: project-url
Dynamic: requires-dist
Dynamic: requires-python
Dynamic: summary
